{
    "market": {
        "symbol": "BTC/USDT:USDT",
        "timeframe": "1h",
        "htf": "4h"
    },
    "strategy": {
        "swingsLength": 43,
        "ob_mitigation": "Close",
        "use_adx_filter": false,
        "adx_period": 11,
        "adx_threshold": 21
    },
    "risk": {
        "margin_mode": "isolated",
        "risk_per_trade_pct": 1.97,
        "risk_reward_ratio": 2.62,
        "leverage": 11,
        "trailing_stop_activation_rr": 3.14,
        "trailing_stop_callback_rate_pct": 0.55,
        "atr_multiplier_sl": 1.05,
        "min_sl_pct": 0.9
    },
    "behavior": {
        "use_longs": true,
        "use_shorts": true
    }
}