{
    "market": {
        "symbol": "AVAX/USDT:USDT",
        "timeframe": "30m",
        "htf": "2h"
    },
    "strategy": {
        "swingsLength": 32,
        "ob_mitigation": "Close",
        "use_adx_filter": false,
        "adx_period": 14,
        "adx_threshold": 21
    },
    "risk": {
        "margin_mode": "isolated",
        "risk_per_trade_pct": 1.69,
        "risk_reward_ratio": 3.26,
        "min_leverage": 7,
        "max_leverage": 24,
        "sl_buffer_atr_mult": 0.458,
        "trailing_stop_activation_rr": 1.82,
        "trailing_stop_callback_rate_pct": 0.54
    },
    "behavior": {
        "use_longs": true,
        "use_shorts": true
    }
}